cmndseven_cli/__init__.py
cmndseven_cli/assets/bpmn-viewer.production.min.js
cmndseven_cli/assets/index.js
cmndseven_cli/assets/instance.html
cmndseven_cli/assets/puppeteer.production.min.js
cmndseven_cli/assets/puppeteer.production.min.js.LICENSE.txt
cmndseven_cli/assets/skeleton.html
cmndseven_cli-0.2.1.dist-info/LICENSE
cmndseven_cli-0.2.1.dist-info/WHEEL
cmndseven_cli-0.2.1.dist-info/METADATA
cmndseven_cli-0.2.1.dist-info/entry_points.txt
cmndseven_cli-0.2.1.dist-info/RECORD
